Workbook

Sheet Cover
B2: AI-Driven Financial Analytics Platform
B3: ESG Investment Decision Framework
B5: Company: Apple Inc. (AAPL)
B6: Sector: Technology
B7: Model Type: 3-Statement + DCF Valuation
B8: Base Year: FY2023
B9: Projection: FY2024E - FY2026E
B10: Prepared By: Vansh Goyal
B11: Date: 22 March 2026

Sheet Assumptions
A1: REVENUE ASSUMPTIONS
A2: Revenue Growth - FY2024E | B2: =CHOOSE($B$23, B30, C30, D30) -> 0.02
A3: Revenue Growth - FY2025E | B3: =CHOOSE($B$23, B31, C31, D31) -> 0.02
A4: Revenue Growth - FY2026E | B4: =CHOOSE($B$23, B32, C32, D32) -> 0.02
A6: MARGIN ASSUMPTIONS
A7: Gross Margin% | B7: 0.441
A8: EBITDA Margin% | B8: 0.321
A9: Net Income Margin% | B9: =CHOOSE($B$23, B33, C33, D33) -> 0.22
A11: BALANCE SHEET ASSUMPTIONS
A12: CAPEX as % of Revenue | B12: 0.028
A13: D&A as % of Revenue | B13: 0.025
A14: Change in Working Capital% | B14: 0.012
A16: DCF ASSUMPTIONS
A17: WACC (Discount Rate) | B17: =CHOOSE($B$23, B34, C34, D34) -> 0.105
A18: Terminal Growth Rate | B18: 0.03
A19: ESG Discount Adjustment | B19: -0.005
A20: ESG - Adjusted WACC | B20: =B17+B19 -> 0.1
A22: SCENARIO TOGGLE
A23: Active Scenario (1=Bear, 2=Base , 3=Bull) | B23: 1 | D23: =CHOOSE(B23, "🐻 BEAR CASE ACTIVE", "📊 BASE CASE ACTIVE", "🐂 BULL CASE ACTIVE") -> 🐻 BEAR CASE ACTIVE | E23: ="Implied Price: $"&TEXT(DCF_Valuation!B24,"0.00") -> Implied Price: $80.38
A27: SCENARIO INPUTS (DO NOT EDIT - auto-feeds model)
A29: Parameter | B29: Bear | C29: Base | D29: Bull
A30: Rev Growth Y1 | B30: 0.02 | C30: 0.04 | D30: 0.09
A31: Rev Growth Y2 | B31: 0.02 | C31: 0.06 | D31: 0.1
A32: Rev Growth Y3 | B32: 0.02 | C32: 0.07 | D32: 0.12
A33: Net Income Margin | B33: 0.22 | C33: 0.253 | D33: 0.28
A34: WACC | B34: 0.105 | C34: 0.09 | D34: 0.08

Sheet Income_Statement
B1: Metric | C1: FY2021A | D1: FY2022A | E1: FY2023A | F1: FY2024E | G1: FY2025E | H1: FY2026E
B3: Revenue ($mn) | C3: 365817 | D3: 394328 | E3: 383285 | F3: =E3*(1+Assumptions!B2) -> 390950.7 | G3: =F3*(1+Assumptions!B3) -> 398769.71 | H3: =G3*(1+Assumptions!B4) -> 406745.11
B5: Gross Profit ($mn) | C5: 152836 | D5: 170782 | E5: 169148 | F5: =F3*Assumptions!B7 -> 172409.26 | G5: =G3*Assumptions!B7 -> 175857.44 | H5: =H3*Assumptions!B7 -> 179374.59
B6: Gross Margin % | C6: =C5/C3 -> 0.4177936 | D6: =D5/D3 -> 0.43309631 | E6: =E5/E3 -> 0.4413113 | F6: =F5/F3 -> 0.441 | G6: =G5/G3 -> 0.441 | H6: =H5/H3 -> 0.441
B8: EBITDA ($mn) | C8: 120233 | D8: 130541 | E8: 123217 | F8: =F3*Assumptions!B8 -> 125495.17 | G8: =G3*Assumptions!B8 -> 128005.08 | H8: =H3*Assumptions!B8 -> 130565.18
B9: EBITDA Margin % | C9: =C8/C3 -> 0.3286698 | D9: =D8/D3 -> 0.33104674 | E9: =E8/E3 -> 0.32147619 | F9: =F8/F3 -> 0.321 | G9: =G8/G3 -> 0.321 | H9: =H8/H3 -> 0.321
B11: D&A ($mn) | C11: 11284 | D11: 11104 | E11: 11519 | F11: =F3*Assumptions!B13 -> 9773.7675 | G11: =G3*Assumptions!B13 -> 9969.2429 | H11: =H3*Assumptions!B13 -> 10168.628
B12: EBIT ($mn) | C12: =C8-C11 -> 108949 | D12: =D8-D11 -> 119437 | E12: =E8-E11 -> 111698 | F12: =F8-F11 -> 115721.41 | G12: =G8-G11 -> 118035.84 | H12: =H8-H11 -> 120396.55
B14: Net Income ($mn) | C14: 94680 | D14: 99803 | E14: 96995 | F14: =F3*Assumptions!B9 -> 86009.154 | G14: =G3*Assumptions!B9 -> 87729.337 | H14: =H3*Assumptions!B9 -> 89483.924
B15: Net Margin % | C15: =C14/C3 -> 0.25881793 | D15: =D14/D3 -> 0.25309641 | E15: =E14/E3 -> 0.25306234 | F15: =F14/F3 -> 0.22 | G15: =G14/G3 -> 0.22 | H15: =H14/H3 -> 0.22
B17: EPS ($) | C17: 5.61 | D17: 6.11 | E17: 6.13 | F17: =F14/15500 -> 5.5489777 | G17: =G14/15300 -> 5.7339436 | H17: =H14/15100 -> 5.9260877

Sheet Balance_Sheet
B1: Metric | C1: FY2021A | D1: FY2022A | E1: FY2023A | F1: FY2024E | G1: FY2025E | H1: FY2026E
B3: ASSETS
B4: Cash & Cash Equivalents ($mn) | C4: 34940 | D4: 23646 | E4: 29965 | F4: =E4*(1+Assumptions!B2) -> 30564.3 | G4: =F4*(1+Assumptions!B3) -> 31175.586 | H4: =G4*(1+Assumptions!B4) -> 31799.098
B5: Total Current Assets ($mn) | C5: 134836 | D5: 135405 | E5: 143566 | F5: =E5*(Income_Statement!F3/Income_Statement!E3) -> 146437.32 | G5: =F5*(Income_Statement!G3/Income_Statement!F3) -> 149366.07 | H5: =G5*(Income_Statement!H3/Income_Statement!G3) -> 152353.39
B6: Total Assets ($mn) | C6: 351002 | D6: 352755 | E6: 352583 | F6: =E6*(Income_Statement!F3/Income_Statement!E3) -> 359634.66 | G6: =F6*(Income_Statement!G3/Income_Statement!F3) -> 366827.35 | H6: =G6*(Income_Statement!H3/Income_Statement!G3) -> 374163.9
B8: LIABILITIES
B9: Total Debt ($mn) | C9: 124719 | D9: 132480 | E9: 123930 | F9: =E9*0.98 -> 121451.4 | G9: =F9*0.97 -> 117807.86 | H9: =G9*0.96 -> 113095.54
B10: Total Liabilities ($mn) | C10: 287912 | D10: 302083 | E10: 290437 | F10: =E10*(Income_Statement!F3/Income_Statement!E3) -> 296245.74 | G10: =F10*(Income_Statement!G3/Income_Statement!F3) -> 302170.65 | H10: =G10*(Income_Statement!H3/Income_Statement!G3) -> 308214.07
B12: EQUITY
B13: Total Equity ($mn) | C13: =C6-C10 -> 63090 | D13: =D6-D10 -> 50672 | E13: =E6-E10 -> 62146 | F13: =F6-F10 -> 63388.92 | G13: =G6-G10 -> 64656.698 | H13: =H6-H10 -> 65949.832
B15: KEY RATIOS
B16: Debt/Asset Ratio | C16: =C9/C6 -> 0.35532276 | D16: =D9/D6 -> 0.37555811 | E16: =E9/E6 -> 0.35149171 | F16: =F9/F6 -> 0.33770772 | G16: =G9/G6 -> 0.32115342 | H16: =H9/H6 -> 0.30226204
B17: Equity Multiplier | C17: =C6/C13 -> 5.5635124 | D17: =D6/D13 -> 6.9615369 | E17: =E6/E13 -> 5.6734625 | F17: =F6/F13 -> 5.6734625 | G17: =G6/G13 -> 5.6734625 | H17: =H6/H13 -> 5.6734625

Sheet Cash_Flow
B1: Metric | C1: FY2021A | D1: FY2022A | E1: FY2023A | F1: FY2024E | G1: FY2025E | H1: FY2026E
B3: Net Income ($mn) | C3: =Income_Statement!C14 -> 94680 | D3: =Income_Statement!D14 -> 99803 | E3: =Income_Statement!E14 -> 96995 | F3: =Income_Statement!F14 -> 86009.154 | G3: =Income_Statement!G14 -> 87729.337 | H3: =Income_Statement!H14 -> 89483.924
B5: Add: D&A ($mn) | C5: =Income_Statement!C11 -> 11284 | D5: =Income_Statement!D11 -> 11104 | E5: =Income_Statement!E11 -> 11519 | F5: =Income_Statement!F11 -> 9773.7675 | G5: =Income_Statement!G11 -> 9969.2429 | H5: =Income_Statement!H11 -> 10168.628
B6: Less: Capex ($mn) | C6: -10708 | D6: -10708 | E6: -10959 | F6: =-Income_Statement!F3*Assumptions!B12 -> -10946.62 | G6: =-Income_Statement!G3*Assumptions!B12 -> -11165.552 | H6: =-Income_Statement!H3*Assumptions!B12 -> -11388.863
B7: Less: Change in Working Capital ($mn) | C7: -1200 | D7: -900 | E7: -1100 | F7: =-Income_Statement!F3*Assumptions!B14 -> -4691.4084 | G7: =-Income_Statement!G3*Assumptions!B14 -> -4785.2366 | H7: =-Income_Statement!H3*Assumptions!B14 -> -4880.9413
B9: Free Cash Flow ($mn) | C9: =C3+C5+C6+C7 -> 94056 | D9: =D3+D5+D6+D7 -> 99299 | E9: =E3+E5+E6+E7 -> 96455 | F9: =F3+F5+F6+F7 -> 80144.894 | G9: =G3+G5+G6+G7 -> 81747.791 | H9: =H3+H5+H6+H7 -> 83382.747
B10: FCF Margin % | C10: =C9/Income_Statement!C3 -> 0.25711216 | D10: =D9/Income_Statement!D3 -> 0.25181828 | E10: =E9/Income_Statement!E3 -> 0.25165347 | F10: =F9/Income_Statement!F3 -> 0.205 | G10: =G9/Income_Statement!G3 -> 0.205 | H10: =H9/Income_Statement!H3 -> 0.205

Sheet DCF_Valuation
A1: SECTION 1: PROJECTED FREE CASH FLOWS
A3: Year Label | B3: FY2024E | C3: FY2025E | D3: FY2026E
A4: Free Cash Flow | B4: =Cash_Flow!F9 -> 80144.894 | C4: =Cash_Flow!G9 -> 81747.791 | D4: =Cash_Flow!H9 -> 83382.747
A5: Discount Factor | B5: =1/(1+F34)^1 -> 0.90497738 | C5: =1/(1+F34)^2 -> 0.81898405 | D5: =1/(1+F34)^3 -> 0.74116204
A6: PV of FCF | B6: =B4*B5 -> 72529.315 | C6: =C4*C5 -> 66950.137 | D6: =D4*D5 -> 61800.127
A8: SECTION 2: TERMINAL VALUE
A10: Terminal Year FCF | B10: =D4 -> 83382.747
A11: Terminal Growth Rate | B11: =F35 -> 0.03
A12: WACC (ESG-Adjusted) | B12: =Assumptions!B20 -> 0.1
A13: Terminal Value | B13: =B10*(1+B11)/(B12-B11) -> 1226917.6
A14: PV of Terminal Value | B14: =B13/(1+F35)^3 -> 1122803.4
A16: SECTION 3: VALUATION SUMMARY
A18: Sum of PV (FCFs) | B18: =SUM(B6:D6) -> 201279.58
A19: PV of Terminal Value | B19: =B14 -> 1122803.4
A20: Enterprise Value ($mn) | B20: =B18+B19 -> 1324083
A21: Less: Net Debt ($mn) | B21: -83000
A22: Equity Value ($mn) | B22: =B20+B21 -> 1241083
A23: Shares Oustanding (mn) | B23: 15441
A24: Implied Share Price | B24: =B22/B23 -> 80.375815
A25: Current Price (FY2023) | B25: 189.3
A26: Upside / Downside% | B26: =(B24-B25)/B25 -> -0.5754051
A28: SCENARIO ANALYSIS
A29: Scenario | B29: Rev Growth | C29: Net Margin | D29: WACC | E29: Implied Price
A30: Bear Case | B30: 0.02 | C30: 0.22 | D30: 0.105 | E30: =((Income_Statement!$E$3*(1+B30)*(C30+Assumptions!$B$13-Assumptions!$B$12-Assumptions!$B$14))/(1+D30) +(Income_Statement!$E$3*(1+B30)^2*(C30+Assumptions!$B$13-Assumptions!$B$12-Assumptions!$B$14))/(1+D30)^2 +(Income_Statement!$E$3*(1+B30)^3*(C30+Assumptions!$B$13-Assumptions!$B$12-Assumptions!$B$14))/(1+D30)^3 +(Income_Statement!$E$3*(1+B30)^3*(C30+Assumptions!$B$13-Assumptions!$B$12-Assumptions!$B$14)*(1+Assumptions!$B$18))/((D30-Assumptions!$B$18)*(1+D30)^3) -83000)/15441 -> 62.625563
A31: Base Case | B31: 0.06 | C31: 0.253 | D31: 0.09 | E31: =((Income_Statement!$E$3*(1+B31)*(C31+Assumptions!$B$13-Assumptions!$B$12-Assumptions!$B$14))/(1+D31) +(Income_Statement!$E$3*(1+B31)^2*(C31+Assumptions!$B$13-Assumptions!$B$12-Assumptions!$B$14))/(1+D31)^2 +(Income_Statement!$E$3*(1+B31)^3*(C31+Assumptions!$B$13-Assumptions!$B$12-Assumptions!$B$14))/(1+D31)^3 +(Income_Statement!$E$3*(1+B31)^3*(C31+Assumptions!$B$13-Assumptions!$B$12-Assumptions!$B$14)*(1+Assumptions!$B$18))/((D31-Assumptions!$B$18)*(1+D31)^3) -83000)/15441 -> 104.66136
A32: Bull Case | B32: 0.09 | C32: 0.28 | D32: 0.08 | E32: =((Income_Statement!$E$3*(1+B32)*(C32+Assumptions!$B$13-Assumptions!$B$12-Assumptions!$B$14))/(1+D32) +(Income_Statement!$E$3*(1+B32)^2*(C32+Assumptions!$B$13-Assumptions!$B$12-Assumptions!$B$14))/(1+D32)^2 +(Income_Statement!$E$3*(1+B32)^3*(C32+Assumptions!$B$13-Assumptions!$B$12-Assumptions!$B$14))/(1+D32)^3 +(Income_Statement!$E$3*(1+B32)^3*(C32+Assumptions!$B$13-Assumptions!$B$12-Assumptions!$B$14)*(1+Assumptions!$B$18))/((D32-Assumptions!$B$18)*(1+D32)^3) -83000)/15441 -> 154.03166
E34: WACC Input | F34: =Assumptions!B17 -> 0.105
E35: Terminal Grwoth Input | F35: =Assumptions!B18 -> 0.03
A36: =B24 -> 80.375815 | B36: 0.075 | C36: 0.08 | D36: 0.085 | E36: 0.09 | F36: 0.095 | G36: 0.1 | H36: 0.105
A37: 0.02 | B37: 73.26102 | C37: 73.136252 | D37: 73.013377 | E37: 72.892355 | F37: 72.773149 | G37: 72.655723 | H37: 72.540039
A38: 0.025 | B38: 76.912823 | C38: 76.788055 | D38: 76.66518 | E38: 76.544158 | F38: 76.424952 | G38: 76.307525 | H38: 76.191842
A39: 0.03 | B39: 81.096796 | C39: 80.972028 | D39: 80.849152 | E39: 80.72813 | F39: 80.608925 | G39: 80.491498 | H39: 80.375815
A40: 0.035 | B40: 85.935529 | C40: 85.810761 | D40: 85.687886 | E40: 85.566864 | F40: 85.447658 | G40: 85.330231 | H40: 85.214548
A41: 0.04 | B41: 91.592483 | C41: 91.467715 | D41: 91.344839 | E41: 91.223818 | F41: 91.104612 | G41: 90.987185 | H41: 90.871502

Sheet Peer_Comparison
B2: ESG-Integrated Peer Comparison - Coverage Universe (FY2023)
B3: Source: SQL Data Warehouse + Python ESG Scoring Engine + AAPL DCF Model
B6: Ticker | C6: Company | D6: Sector | E6: ESG Rating | F6: ESG Score | G6: Carbon Intensity | H6: Revenue $mn | I6: Net Margin % | J6: EBITDA Mragin % | K6: 2yr CAGR % | L6: WACC Used % | M6: ESG WACC Adj % | N6: Adj WACC % | O6: Implied Upside % | P6: Investment Tier | Q6: Analyst View | S6: ESG-ADJUSTED WACC METHODOLOGY
B7: MSFT | C7: Microsoft Corporation | D7: Technology | E7: AAA | F7: 88.4 | G7: 1.7 | H7: 211915 | I7: 0.3415 | J7: 0.4993 | K7: 0.1221 | L7: 0.09 | M7: -0.0075 | N7: =L7+M7 -> 0.0825 | O7: 0.185 | P7: Strong Buy | Q7: Premium ESG +Financials justify valuation | S7: ESG Rating → WACC Adjustment:
B8: AAPL | C8: Apple Inc. | D8: Technology | E8: AAA | F8: 84.5 | G8: 2.6 | H8: 383285 | I8: 0.2531 | J8: 0.3215 | K8: 0.0236 | L8: 0.09 | M8: -0.005 | N8: =L8+M8 -> 0.085 | O8: =(DCF_Valuation!B24-DCF_Valuation!B25)/DCF_Valuation!B25 -> -0.5754051 | P8: Buy | Q8: DCF suggests overvaluation despite strong ESG | S8: AAA → -0.75% (lowest risk)
B9: NEE | C9: NextEra Energy Inc. | D9: Utilities | E9: AAA | F9: 83.2 | G9: 6.5 | H9: 24521 | I9: 0.1475 | J9: 0.4825 | K9: 0.1983 | L9: 0.09 | M9: -0.0075 | N9: =L9+M9 -> 0.0825 | O9: 0.22 | P9: Buy | Q9: Clean energy leader, Strong ESG-driven growth | S9: AA → -0.25% (low risk)
B10: UL | C10: Unilever PLC | D10: Consumer Staples | E10: AA | F10: 77.7 | G10: 8.7 | H10: 59580 | I10: 0.1199 | J10: 0.1704 | K10: 0.0656 | L10: 0.09 | M10: -0.0025 | N10: =L10+M10 -> 0.0875 | O10: 0.08 | P10: Hold | Q10: Stable ESG profile, limited near-term upside | S10: A → 0.00% (neutral)
B11: JNJ | C11: Johnson & Johnson | D11: Healthcare | E11: AA | F11: 70.9 | G11: 8.1 | H11: 85159 | I11: 0.1579 | J11: 0.2594 | K11: -0.047 | L11: 0.09 | M11: -0.0025 | N11: =L11+M11 -> 0.0875 | O11: 0.05 | P11: Hold | Q11: Pharma spinoff impact; ESG stable, growth uncertain | S11: BBB → +0.50% (elevated risk)
B12: JPM | C12: JPMorgan Chase & Co. | D12: Financials | E12: AA | F12: 65.4 | G12: 11.2 | H12: 154788 | I12: 0.3201 | J12: 0.3498 | K12: 0.1105 | L12: 0.09 | M12: 0 | N12: =L12+M12 -> 0.09 | O12: 0.12 | P12: Buy | Q12: Strong financials offset moderate ESG score | S12: BB → +0.75% (high risk)
B13: AMZN | C13: Amazon.com INC. | D13: Consumer Discr. | E13: A | F13: 57.8 | G13: 18.3 | H13: 574785 | I13: 0.0529 | J13: 0.1491 | K13: 0.1061 | L13: 0.095 | M13: 0 | N13: =L13+M13 -> 0.095 | O13: -0.05 | P13: Underperform | Q13: Improving ESG trend but thin margins concern | S13: B → +1.00% (very high risk)
B14: TSLA | C14: Tesla Inc. | D14: Consumer Discr. | E14: A | F14: 53.5 | G14: 12.5 | H14: 96773 | I14: 0.1547 | J14: 0.1339 | K14: 0.341 | L14: 0.095 | M14: 0 | N14: =L14+M14 -> 0.095 | O14: 0.08 | P14: Buy | Q14: EV growth story; governance concerns cap ESG upside | S14: Source: Adapted from MSCI ESG
B15: CVX | C15: Chevron Corporation | D15: Energy | E15: BBB | F15: 44 | G15: 80.1 | H15: 196913 | I15: 0.1085 | J15: 0.1802 | K15: 0.1249 | L15: 0.105 | M15: 0.005 | N15: =L15+M15 -> 0.11 | O15: -0.08 | P15: Underperform | Q15: High carbon intensity; ESG risk premium applied | S15: Risk Premium Framework
B16: XOM | C16: Exxon Mobil Corporation | D16: Energy | E16: BBB | F16: 40.6 | G16: 87.3 | H16: 334697 | I16: 0.1076 | J16: 0.1674 | K16: 0.0996 | L16: 0.105 | M16: 0.0075 | N16: =L16+M16 -> 0.1125 | O16: -0.12 | P16: Underperform | Q16: Highest carbon intensity; ESG headwinds structural
B18: Summary Statistics
B19: ESG Leaders (AAA/AA) | C19: =COUNTIF(E7:E16,"AAA")+COUNTIF(E7:E16,"AA") -> 6
B20: Avg ESG Score | C20: =AVERAGE(F7:F16) -> 66.6
B21: Avg Adj WACC | C21: =AVERAGE(N7:N16) -> 0.09275
B22: Companies with Upside | C22: =COUNTIF(O7:O16,">0") -> 6
B23: Avg Net Margin | C23: =AVERAGE(I7:I16) -> 0.17637
B42: AI SCORING METHODOLOGY
B43: Financial Pillar (35%): | C43: Net Margin, EBITDA Margin,Free Cash Flow, ROE
B44: ESG Pillar (40%): | C44: Composite ESG Score, Carbon Intensity, 2024 ESG Prediction,ESG Momentum Trend
B45: Sentiment Pillar (25%): | C45: VADER NLP analysis of financial news headlines (6 per company)
B46: Model: | C46: Rule-based weighted scoring with Linear Regression ESG forecasting
